pyssage/__init__.py
pyssage/anisotropy.py
pyssage/classes.py
pyssage/common.py
pyssage/connections.py
pyssage/correlogram.py
pyssage/distances.py
pyssage/graph.py
pyssage/mantel.py
pyssage/quadvar.py
pyssage/utils.py
tests/__init__.py
tests/test_anisotropy.py
tests/test_common.py
tests/test_connections.py
tests/test_correlogram.py
tests/test_distances.py
tests/test_graph.py
tests/test_mantel.py
tests/test_quadvar.py
tests/test_utils.py
pyssage-0.1.2.dist-info/LICENSE
pyssage-0.1.2.dist-info/METADATA
pyssage-0.1.2.dist-info/WHEEL
pyssage-0.1.2.dist-info/top_level.txt
pyssage-0.1.2.dist-info/RECORD
