Metadata-Version: 2.1
Name: pyssage
Version: 0.1.2
Summary: python version of some of the analyses from PASSaGE 2
Home-page: https://github.com/msrosenberg/pyssage
Author: Michael S. Rosenberg
Author-email: msrosenberg@vcu.edu
License: GPLv3
Platform: UNKNOWN
Classifier: Programming Language :: Python :: 3
Classifier: Operating System :: OS Independent
Requires-Python: >=3.6
